main.py
rustman-0.1.0.dist-info/METADATA
rustman-0.1.0.dist-info/WHEEL
rustman-0.1.0.dist-info/top_level.txt
rustman-0.1.0.dist-info/RECORD
