Metadata-Version: 2.4
Name: rustman
Version: 0.1.0
Summary: Reserving namespace for a new project
Requires-Python: >=3.13
